{
  "building_name": "传统民居（孔祥顺宅）",
  "measureName": "传统民居（孔祥顺宅）",
  "requestName": "管理员",
  "requestPhone": "17034642998",
  "requestDate": "2024-01-26 08:45:49",
  "valueIntroduction": "孔祥顺宅为桂林市灌阳县灌阳镇秀凤村孔家屯内一处清代砖木结构传统民居，建于1644-1911年间，现存两层建筑体量，总建筑面积420平方米。该建筑采用两进院落布局，主体为硬山式屋顶，两侧以青砖砌筑山墙，中部以木框架承重，门梁采用木质构件，山墙门框上方题有\"燕翼贻谋\"字样，兼具防火与装饰功能的马头墙高出屋面。建筑平面推测符合桂北地区\"三间两厢\"的典型形制，空间组织紧凑，功能分区明确。作为灌阳地区保存较完整的清代民居，其砖木混合结构、硬山屋顶与题字山墙等元素，既体现了湘赣移民带来的汉族建筑技艺，又融合了当地材料与营造传统，反映了清代桂东北民居的地域特色。现存建筑质量中等，未经过现代修缮，其原始构架与细部保存了清代民间工匠的营造智慧，对研究灌阳盆地传统聚落建筑形制与文化融合具有实证价值。",
  "nowFunction": "其他",
  "structureType": "砖木结构",
  "buildFloor": 2,
  "buildArea": 420.0,
  "buildLandArea": 420.0,
  "propertyType": "私产",
  "propertyOwner": "孔祥顺",
  "city": "桂林市",
  "county": "灌阳县",
  "build_year": "清（1644-1911年）",
  "address": "灌阳镇秀凤村孔家屯",
  "status": "PASS",
  "publishTime": "2023-09-25 00:00:00",
  "protectionRepair": "未修缮",
  "buildingQuality": "中",
  "protectionRepairDept": "住建局",
  "buildingApproval": "已批准",
  "signTab": "已挂牌",
  "cityType": "国家历史文化名城",
  "batch": "第二批",
  "publishInfo": "已发布",
  "cityLevel": "自治区级",
  "nowFunctionMsg": "闲置",
  "historicalBuildtFiles": [
    {
      "createBy": "admin",
      "createTime": "2024-01-29 17:09:54",
      "updateBy": "admin",
      "updateTime": "2024-01-29 17:09:54",
      "fileHistoricalBuildId": "1750681412128075778",
      "fileId": "1751895433363714050",
      "fileName": "灌阳县人民政府关于公布第二批历史建筑的通知.pdf",
      "fileTypeId": null,
      "fileType": "公布文件",
      "filePath": "70b82dd56f2f4020ada5a0952d2236ff.pdf",
      "fileExt": null,
      "fileSpace": null,
      "fileUserId": null,
      "fileUserName": null
    },
    {
      "createBy": "admin",
      "createTime": "2024-01-29 17:09:54",
      "updateBy": "admin",
      "updateTime": "2024-01-29 17:09:54",
      "fileHistoricalBuildId": "1750681412128075778",
      "fileId": "1751895433376296962",
      "fileName": "灌阳镇秀凤村孔家屯传统民居(孔祥顺宅)2.jpg",
      "fileTypeId": null,
      "fileType": "挂牌文件",
      "filePath": "a57dd19c5d204d578cfb3f0751663a10.jpg",
      "fileExt": null,
      "fileSpace": null,
      "fileUserId": null,
      "fileUserName": null
    }
  ],
  "districtCode": "450327000000",
  "historicalBuildImages": [
    {
      "createBy": "admin",
      "createTime": "2024-01-29 00:00:00",
      "updateBy": "admin",
      "updateTime": "2024-01-29 00:00:00",
      "imageMeasureId": "1750681412128075778",
      "imageId": "1751895433405657090",
      "imageName": "侧.jpg",
      "imageAuthor": null,
      "imageDate": null,
      "imagePath": "6f81f7d915154a9cb96a173070abc988.jpg",
      "imageType": "侧立面"
    },
    {
      "createBy": "admin",
      "createTime": "2024-01-29 00:00:00",
      "updateBy": "admin",
      "updateTime": "2024-01-29 00:00:00",
      "imageMeasureId": "1750681412128075778",
      "imageId": "1751895433418240002",
      "imageName": "细2.jpg",
      "imageAuthor": null,
      "imageDate": null,
      "imagePath": "99afc817971a45269b9f445444103a01.jpg",
      "imageType": "建筑细部"
    },
    {
      "createBy": "admin",
      "createTime": "2024-01-29 00:00:00",
      "updateBy": "admin",
      "updateTime": "2024-01-29 00:00:00",
      "imageMeasureId": "1750681412128075778",
      "imageId": "1751895433430822914",
      "imageName": "细1.jpg",
      "imageAuthor": null,
      "imageDate": null,
      "imagePath": "30e03e48d5da444d95681a88ff5656b9.jpg",
      "imageType": "建筑细部"
    },
    {
      "createBy": "admin",
      "createTime": "2024-01-29 00:00:00",
      "updateBy": "admin",
      "updateTime": "2024-01-29 00:00:00",
      "imageMeasureId": "1750681412128075778",
      "imageId": "1751895433443405826",
      "imageName": "内2.jpg",
      "imageAuthor": null,
      "imageDate": null,
      "imagePath": "aa479b4741184250877cb5a920e46d57.jpg",
      "imageType": "内部全景"
    },
    {
      "createBy": "admin",
      "createTime": "2024-01-29 00:00:00",
      "updateBy": "admin",
      "updateTime": "2024-01-29 00:00:00",
      "imageMeasureId": "1750681412128075778",
      "imageId": "1751895433451794434",
      "imageName": "内1.jpg",
      "imageAuthor": null,
      "imageDate": null,
      "imagePath": "9aaa7b08f9cc41cc9c7085ec8de6ba8a.jpg",
      "imageType": "内部全景"
    },
    {
      "createBy": "admin",
      "createTime": "2024-01-29 00:00:00",
      "updateBy": "admin",
      "updateTime": "2024-01-29 00:00:00",
      "imageMeasureId": "1750681412128075778",
      "imageId": "1751895433460183041",
      "imageName": "外.jpg",
      "imageAuthor": null,
      "imageDate": null,
      "imagePath": "b88bca9ec3d94e05856d348ce1428271.jpg",
      "imageType": "外部全景"
    },
    {
      "createBy": "admin",
      "createTime": "2024-01-29 00:00:00",
      "updateBy": "admin",
      "updateTime": "2024-01-29 00:00:00",
      "imageMeasureId": "1750681412128075778",
      "imageId": "1751895433468571649",
      "imageName": "正.jpg",
      "imageAuthor": null,
      "imageDate": null,
      "imagePath": "520437f50a134d60b5c11fbed16bad06.jpg",
      "imageType": "正立面"
    }
  ],
  "source": "GX_Buildings",
  "A2_content": "孔祥顺宅为桂林市灌阳县灌阳镇秀凤村孔家屯内一处清代砖木结构传统民居，建于1644-1911年间，现存两层建筑体量，总建筑面积420平方米。该建筑采用两进院落布局，主体为硬山式屋顶，两侧以青砖砌筑山墙，中部以木框架承重，门梁采用木质构件，山墙门框上方题有\"燕翼贻谋\"字样，兼具防火与装饰功能的马头墙高出屋面。建筑平面推测符合桂北地区\"三间两厢\"的典型形制，空间组织紧凑，功能分区明确。作为灌阳地区保存较完整的清代民居，其砖木混合结构、硬山屋顶与题字山墙等元素，既体现了湘赣移民带来的汉族建筑技艺，又融合了当地材料与营造传统，反映了清代桂东北民居的地域特色。现存建筑质量中等，未经过现代修缮，其原始构架与细部保存了清代民间工匠的营造智慧，对研究灌阳盆地传统聚落建筑形制与文化融合具有实证价值。"
}