{
  "building_name": "儒林第",
  "measureName": "儒林第",
  "city": "钦州市",
  "county": "灵山县",
  "address": "檀圩镇东岸村",
  "status": "PASS",
  "publishTime": "2022-12-29 00:00:00",
  "cityType": "非名城",
  "measureFlag": "0",
  "publishInfo": "已发布",
  "cityLevel": "自治区级",
  "disclosureTime": "2022-12-29",
  "disclosureFlag": "1",
  "districtCode": "450721000000",
  "source": "GX_Buildings",
  "A2_content": "儒林第位于钦州市灵山县檀圩镇东岸村，为清代传统民居建筑。该建筑采用广府民居典型的一进一天井三开间布局，中轴线对称分布照壁、天井及主厅，两侧设厢房与连廊，整体格局严谨。墙体以青砖砌筑，局部采用石质墙基，屋面为硬山式，檐口装饰简洁的灰塑纹样，体现出清代岭南民居的营造技艺。建筑坐向顺应地形，主立面朝向开阔地带，兼具实用性与风水考量。作为灵山县现存较完整的清代宅第，其空间组织反映了传统宗族礼制观念，厢房与主厅的等级划分清晰，天井兼具采光与排水功能。该建筑是研究桂东南地区清代民居形制、地方宗族文化的重要实物遗存，其选址与构造细节展现了广府建筑文化与当地自然环境的适应性结合。",
  "valueIntroduction": "儒林第位于钦州市灵山县檀圩镇东岸村，为清代传统民居建筑。该建筑采用广府民居典型的一进一天井三开间布局，中轴线对称分布照壁、天井及主厅，两侧设厢房与连廊，整体格局严谨。墙体以青砖砌筑，局部采用石质墙基，屋面为硬山式，檐口装饰简洁的灰塑纹样，体现出清代岭南民居的营造技艺。建筑坐向顺应地形，主立面朝向开阔地带，兼具实用性与风水考量。作为灵山县现存较完整的清代宅第，其空间组织反映了传统宗族礼制观念，厢房与主厅的等级划分清晰，天井兼具采光与排水功能。该建筑是研究桂东南地区清代民居形制、地方宗族文化的重要实物遗存，其选址与构造细节展现了广府建筑文化与当地自然环境的适应性结合。"
}