{
  "A2_content": "-11- 全州县东山瑶族乡上塘村\n\n第五批中国传统村落 第二批广西传统村落\n\n \n\n一、村落概况\n\n东山瑶族乡位于全州县最东部，东北与湖南省道县、双牌县、零陵区相邻，乡内大部分属高寒山区。上塘村位于东山瑶族乡东北部，距乡政府驻地约 6 公里，村落占地约 450 亩，人口约 1160 人，皆为瑶族。上塘村地处湘桂古道都庞岭山脉北段，汉瑶民族融合紧密，村落建筑风格、村民服饰都已汉化。上塘村于 2019 年列入第五批中国传统村落名录。\n\n二、历史源流\n\n上塘村中心有一面积约 100 亩的池塘，当地称为华塘，上塘村以前也因此而叫做华塘村。村民主要为盘、奉二姓，其中奉氏先祖于元末明初自江西太和县迁至全州，在定居上塘村前，曾先后迁居于东山乡的白岭六亩田、分水、塘背、石枧坪等村。因井源缺水，无水灌溉，致水田无法耕作，后迁居至汉族人聚居较多的黄蜡洞水源头。由于奉氏族群常受排挤欺凌，无法安居，再次迁回石枧坪，最后举族迁至上塘村定居至今。\n\n三、村落格局\n\n上塘村地处群山环抱的一处小型平地，西面有一缓坡丘陵，植被茂密。传统建筑集中分布在村落西面，主要围绕华塘布局。建筑背靠缓坡山体，依水塘岸线转折，朝向不拘。华塘中部被一小路分隔为一大一小 2 个水面，华堂母校就位于 2 个水面分隔处，构成村落景观的视觉中心。村落最主要的道路沿华塘修筑，大块青石铺就，总长约 2.1 公里，民居、祠堂等传统建筑沿路分布。\n\n \n\n \n\n四、传统建筑\n\n村落现有明清至民国时期的传统建筑约 150座，主要环绕水塘布局。传统建筑体量不大，多为单层硬山屋顶，青砖墙体，青石砌筑墙基，部分建筑采用门楼式大门，以浮雕或彩绘装饰。建筑整体造型简洁朴实，风格基本汉化，但部分民居内堂屋的布局仍保留有体现瑶族传统生活习俗的火塘。\n\n \n\n \n\n \n\n传统建筑中最具代表性的是位于华塘畔西南面的民国私塾——华塘学府。该建筑为小青瓦屋面、砖木结构，占地约 500 平方米，分上下两层，大门及窗户上方的拱券装饰体现了典型的民国时期建筑风格。华堂学府原来是富裕人家的住宅兼私塾，后改为学堂，现为村公所及文化活动中心。建筑三面环水，坐东北朝西南，布局方正。内部以天井进行功能分隔，空间开敞，便于举办商贸联络交流等活动。同时建筑利用场地高差在南面房间下布置局部负一层，并专门开辟了采光井，使得负一层空间也具备良好的采光通风。\n\n五、历史要素\n\n古水缸：村落内遗存有多个清代青石水缸，形状有椭圆形、长方形、八边形等，通体为整块石材凿制，外面采用线雕、浅浮雕等工艺，雕刻回形纹、花鸟、文字等图案。\n\n古井：沿华塘周边分布有几处水井，均按照使用功能进行了井池用水的分隔。其中位于塘边东北面的一处水井，始建于清代，井池由大块石堆彻而成，分为两级，呈长方形。井泉之水流向华塘中，水质清澈，村民至今仍在使用。",
  "source": "广西传统村落丛书",
  "volume": "上册",
  "chapter": "第二章 湘桂古道传统村落",
  "entry_type": "village",
  "village_number": 11,
  "structureType": "砖木结构",
  "build_year": "清（1644-1911年）",
  "city": "桂林市"
}