{
  "building_name": "城隍廟",
  "measureName": "城隍廟",
  "city": "南宁市",
  "county": "横州市",
  "address": "横州市峦城镇永馨街",
  "A2_content": "现存城隍廟为中轴对称三进式院落，采用砖混结构，黄琉璃瓦屋面，中殿脊顶装饰双龙戏珠，后殿脊顶装饰双凤戏珠。门楣正中悬挂着宽大的门匾，上面镌刻着“城隍廟”，门的两侧有祥龙、祥凤雕塑花窗，造型别致。大门前两侧有两根粗壮的金色立柱，通身彩绘缠柱云龙，龙姿栩栩如生。前殿供奉神灵菩萨；中殿供奉城隍老爷；后殿供奉城隍娘娘；东、西厢房供奉财神爷、土地爷等。每年的农历五月二十七日定为城隍廟会日，历代一直延续庙会日举办菩萨出游的法事活动。",
  "status": "PASS",
  "publishTime": "2022-12-12 00:00:00",
  "measureFlag": "0",
  "publishInfo": "已发布",
  "cityLevel": "自治区级",
  "threedUrl": "https://psgx.nnkcy.com/Attachment/History/倾斜/横州市/城隍庙/0506chenghuangmiao/Data/tileset.json",
  "panoramicVideo": "https://psgx.nnkcy.com/Attachment/History/南宁市横州市/城隍庙/4-全景/chenghuangmiao/chenghuangmiao.html",
  "disclosureTime": "2022-12-12",
  "disclosureFlag": "1",
  "districtCode": "450181000000",
  "source": "GX_Buildings"
}