{
  "building_name": "宾阳县南街东—接龙桥北历史建筑群",
  "measureName": "宾阳县南街东—接龙桥北历史建筑群",
  "requestDate": "2023-10-31 15:50:51",
  "valueIntroduction": "宾阳县南街东—接龙桥北历史建筑群始建于宋朝年间，至今保留下来的民居建筑为多清朝时期建筑，建筑群沿着4米宽的由青石板铺砌的南街两侧整齐排列，民居多为一层或二层的三进至五进院落式建筑，建筑空间布局呈狭长型，砖木结构或土木结构的建筑内部的梁柱、斗拱、檩椽、墙面、天花都雕梁画栋，千姿百态，栩栩如生，古色古香的民居建筑饱含着劳动人民智慧，反映宾阳2100多年发展历史，整个街区透出浓浓的古代要冲、古商埠深厚的文化底蕴。",
  "nowFunction": "混合",
  "structureType": "砖木结构",
  "buildFloor": 2,
  "buildArea": 4458.0,
  "buildLandArea": 5145.0,
  "propertyType": "私产",
  "city": "南宁市",
  "county": "宾阳县",
  "build_year": "清（1644-1911年）",
  "address": "宾阳县宾州镇南街377号、379号、381号、383号、386号、387号、389号、390号、392号、395号、397号、399号、401号、403号、406号、408号、410号、412号、415号、417号、419号、421号、423号、426号、428号、430号、432号、436号、438号、441号、443号、446号、448号、450号、452号、453号",
  "build_type": "居住建筑",
  "A2_content": "宾阳县南街东—接龙桥北历史建筑群始建于宋朝年间，至今保留下来的民居建筑为多清朝时期建筑，建筑群沿着4米宽的由青石板铺砌的南街两侧整齐排列，民居多为一层或二层的三进至五进院落式建筑，建筑空间布局呈狭长型，砖木结构或土木结构的建筑内部的梁柱、斗拱、檩椽、墙面、天花都雕梁画栋，千姿百态，栩栩如生，古色古香的民居建筑饱含着劳动人民智慧，反映宾阳2100多年发展历史，整个街区透出浓浓的古代要冲、古商埠深厚的文化底蕴。",
  "status": "PASS",
  "publishTime": "2020-12-01 00:00:00",
  "protectionRepair": "未修缮",
  "buildingQuality": "中",
  "protectionRepairDept": "住建局",
  "buildingApproval": "已批准",
  "signTab": "已挂牌",
  "cityType": "非名城",
  "measureFlag": "1",
  "batch": "第二批",
  "publishInfo": "已发布",
  "cityLevel": "自治区级",
  "historicalBuildtFiles": [
    {
      "createBy": "admin",
      "createTime": "2023-11-08 22:30:03",
      "updateBy": "admin",
      "updateTime": "2023-11-08 22:30:03",
      "fileHistoricalBuildId": "1559479340119187458",
      "fileId": "1722260194298355714",
      "fileName": "南宁市人民政府关于公布南宁市第二批历史建筑保护名录的通知+市政府办公室.pdf",
      "fileTypeId": null,
      "fileType": "公布文件",
      "filePath": "98299aa3a039484da9798bec65bd29f5.pdf",
      "fileExt": null,
      "fileSpace": null,
      "fileUserId": null,
      "fileUserName": null
    }
  ],
  "threedUrl": "https://psgx.nnkcy.com/Attachment/History/南宁（历）-99-106/53-60（2021.10.25）4/Data/tileset.json",
  "disclosureTime": "2020-12-01",
  "disclosureFlag": "1",
  "districtCode": "450126000000",
  "historicalBuildImages": [
    {
      "createBy": "admin",
      "createTime": "2023-11-08 00:00:00",
      "updateBy": "admin",
      "updateTime": "2023-11-08 00:00:00",
      "imageMeasureId": "1559479340119187458",
      "imageId": "1722260194336104449",
      "imageName": "IMG_20201124_144111.jpg",
      "imageAuthor": null,
      "imageDate": null,
      "imagePath": "fd35f00cee49402eb5e4b2699c9090e1.jpg",
      "imageType": "侧立面"
    },
    {
      "createBy": "admin",
      "createTime": "2023-11-08 00:00:00",
      "updateBy": "admin",
      "updateTime": "2023-11-08 00:00:00",
      "imageMeasureId": "1559479340119187458",
      "imageId": "1722260194344493057",
      "imageName": "picture_2020_11_24_14_29_47_505.jpg",
      "imageAuthor": null,
      "imageDate": null,
      "imagePath": "f598de55e2f54da8861557c1b9b34897.jpg",
      "imageType": "侧立面"
    },
    {
      "createBy": "admin",
      "createTime": "2023-11-08 00:00:00",
      "updateBy": "admin",
      "updateTime": "2023-11-08 00:00:00",
      "imageMeasureId": "1559479340119187458",
      "imageId": "1722260194357075970",
      "imageName": "接龙桥北.jpg",
      "imageAuthor": null,
      "imageDate": null,
      "imagePath": "79a3a755d91f437dbbf1d7c8821bf58d.jpg",
      "imageType": "正立面"
    },
    {
      "createBy": "admin",
      "createTime": "2023-11-08 00:00:00",
      "updateBy": "admin",
      "updateTime": "2023-11-08 00:00:00",
      "imageMeasureId": "1559479340119187458",
      "imageId": "1722260194365464578",
      "imageName": "DJI_0196.jpg",
      "imageAuthor": null,
      "imageDate": null,
      "imagePath": "8096d532aa4b49d1bd3055774cff99cb.jpg",
      "imageType": "正立面"
    },
    {
      "createBy": "admin",
      "createTime": "2023-11-08 00:00:00",
      "updateBy": "admin",
      "updateTime": "2023-11-08 00:00:00",
      "imageMeasureId": "1559479340119187458",
      "imageId": "1722260194378047490",
      "imageName": "picture_2020_11_24_14_32_16_304.jpg",
      "imageAuthor": null,
      "imageDate": null,
      "imagePath": "0f3874c249774ed4887bb8c3fbcaf92e.jpg",
      "imageType": "正立面"
    }
  ],
  "source": "GX_Buildings"
}