{
  "building_name": "扬美古建筑群",
  "measureName": "扬美古建筑群",
  "valueIntroduction": "建筑群始建于宋代，在明清时期发展为商业小镇，曾是南宁周边的贸易中心。现存古民居群整体风貌统一协调，民居群现存明代民居1处，清代民居142处，民国民居117处，扬美村内，古街巷石板路、古街、古闸门、古禁碑、古码头、古戏台、古庙宇、古树、古民俗等共同构成扬美村独特的传统历史环境，村中布局的魁星楼、五叠堂、黄氏庄园、举人屋、进士屋、慕义门等古建筑，具有较高的历史保护价值。",
  "nowFunction": "居住",
  "structureType": "砖木结构",
  "buildFloor": 2,
  "buildArea": 3176.0,
  "buildLandArea": 3047.0,
  "propertyType": "私产",
  "city": "南宁市",
  "county": "江南区",
  "build_year": "清（1644-1911年）",
  "address": "江南区江西镇扬美村",
  "build_type": "居住建筑",
  "A2_content": "建筑群始建于宋代，在明清时期发展为商业小镇，曾是南宁周边的贸易中心。现存古民居群整体风貌统一协调，民居群现存明代民居1处，清代民居142处，民国民居117处，扬美村内，古街巷石板路、古街、古闸门、古禁碑、古码头、古戏台、古庙宇、古树、古民俗等共同构成扬美村独特的传统历史环境，村中布局的魁星楼、五叠堂、黄氏庄园、举人屋、进士屋、慕义门等古建筑，具有较高的历史保护价值。",
  "status": "PASS",
  "publishTime": "2020-10-16 00:00:00",
  "protectionRepair": "未修缮",
  "buildingQuality": "中",
  "protectionRepairDept": "住建局",
  "buildingApproval": "已批准",
  "signTab": "已挂牌",
  "cityType": "非名城",
  "measureFlag": "1",
  "batch": "第一批",
  "publishInfo": "已发布",
  "cityLevel": "自治区级",
  "historicalBuildtFiles": [
    {
      "createBy": "admin",
      "createTime": "2023-11-08 21:34:24",
      "updateBy": "admin",
      "updateTime": "2023-11-08 21:34:24",
      "fileHistoricalBuildId": "1559479328438050818",
      "fileId": "1722246192851771394",
      "fileName": "扬美（历）-16_t3.dwg",
      "fileTypeId": null,
      "fileType": "历史建筑平立剖面测绘图片",
      "filePath": "bd3698694bcc450183751425dbcc715c.dwg",
      "fileExt": null,
      "fileSpace": null,
      "fileUserId": null,
      "fileUserName": null
    },
    {
      "createBy": "admin",
      "createTime": "2023-11-08 21:34:24",
      "updateBy": "admin",
      "updateTime": "2023-11-08 21:34:24",
      "fileHistoricalBuildId": "1559479328438050818",
      "fileId": "1722246192864354305",
      "fileName": "扬美（历）-18_t3.dwg",
      "fileTypeId": null,
      "fileType": "历史建筑平立剖面测绘图片",
      "filePath": "3c33b1a601074b5c8944619fb7ec55a2.dwg",
      "fileExt": null,
      "fileSpace": null,
      "fileUserId": null,
      "fileUserName": null
    },
    {
      "createBy": "admin",
      "createTime": "2023-11-08 21:34:24",
      "updateBy": "admin",
      "updateTime": "2023-11-08 21:34:24",
      "fileHistoricalBuildId": "1559479328438050818",
      "fileId": "1722246192876937218",
      "fileName": "扬美（历）-20_t3.dwg",
      "fileTypeId": null,
      "fileType": "历史建筑平立剖面测绘图片",
      "filePath": "68d22b7ac4ae46bbb803f144b30718ce.dwg",
      "fileExt": null,
      "fileSpace": null,
      "fileUserId": null,
      "fileUserName": null
    },
    {
      "createBy": "admin",
      "createTime": "2023-11-08 21:34:24",
      "updateBy": "admin",
      "updateTime": "2023-11-08 21:34:24",
      "fileHistoricalBuildId": "1559479328438050818",
      "fileId": "1722246192885325825",
      "fileName": "扬美（历）-15_t3.dwg",
      "fileTypeId": null,
      "fileType": "历史建筑平立剖面测绘图片",
      "filePath": "819b893c8d4e4c7682c2b84bce42990b.dwg",
      "fileExt": null,
      "fileSpace": null,
      "fileUserId": null,
      "fileUserName": null
    },
    {
      "createBy": "admin",
      "createTime": "2023-11-08 21:34:24",
      "updateBy": "admin",
      "updateTime": "2023-11-08 21:34:24",
      "fileHistoricalBuildId": "1559479328438050818",
      "fileId": "1722246192897908737",
      "fileName": "扬美（历）-07_t3.dwg",
      "fileTypeId": null,
      "fileType": "历史建筑平立剖面测绘图片",
      "filePath": "ca6159ca3b2549ddaf83f1ac034c7878.dwg",
      "fileExt": null,
      "fileSpace": null,
      "fileUserId": null,
      "fileUserName": null
    },
    {
      "createBy": "admin",
      "createTime": "2023-11-08 21:34:24",
      "updateBy": "admin",
      "updateTime": "2023-11-08 21:34:24",
      "fileHistoricalBuildId": "1559479328438050818",
      "fileId": "1722246192910491649",
      "fileName": "扬美（历）-11_t3.dwg",
      "fileTypeId": null,
      "fileType": "历史建筑平立剖面测绘图片",
      "filePath": "efab3b2e75b6433b9b77b1c0a035b3d6.dwg",
      "fileExt": null,
      "fileSpace": null,
      "fileUserId": null,
      "fileUserName": null
    },
    {
      "createBy": "admin",
      "createTime": "2023-11-08 21:34:24",
      "updateBy": "admin",
      "updateTime": "2023-11-08 21:34:24",
      "fileHistoricalBuildId": "1559479328438050818",
      "fileId": "1722246192918880257",
      "fileName": "扬美（历）-13_t3.dwg",
      "fileTypeId": null,
      "fileType": "历史建筑平立剖面测绘图片",
      "filePath": "43696a56b2a245e688faa0b2b7654c35.dwg",
      "fileExt": null,
      "fileSpace": null,
      "fileUserId": null,
      "fileUserName": null
    },
    {
      "createBy": "admin",
      "createTime": "2023-11-08 21:34:24",
      "updateBy": "admin",
      "updateTime": "2023-11-08 21:34:24",
      "fileHistoricalBuildId": "1559479328438050818",
      "fileId": "1722246192931463169",
      "fileName": "扬美（历）-12+_t3.dwg",
      "fileTypeId": null,
      "fileType": "历史建筑平立剖面测绘图片",
      "filePath": "f0f2899b6c994964848977c1d40e519e.dwg",
      "fileExt": null,
      "fileSpace": null,
      "fileUserId": null,
      "fileUserName": null
    },
    {
      "createBy": "admin",
      "createTime": "2023-11-08 21:34:24",
      "updateBy": "admin",
      "updateTime": "2023-11-08 21:34:24",
      "fileHistoricalBuildId": "1559479328438050818",
      "fileId": "1722246192944046081",
      "fileName": "扬美（历）-03_t3.dwg",
      "fileTypeId": null,
      "fileType": "历史建筑平立剖面测绘图片",
      "filePath": "54149560d5554af491fb2a2dbb0425e7.dwg",
      "fileExt": null,
      "fileSpace": null,
      "fileUserId": null,
      "fileUserName": null
    },
    {
      "createBy": "admin",
      "createTime": "2023-11-08 21:34:24",
      "updateBy": "admin",
      "updateTime": "2023-11-08 21:34:24",
      "fileHistoricalBuildId": "1559479328438050818",
      "fileId": "1722246192952434689",
      "fileName": "扬美（历）-01_t3.dwg",
      "fileTypeId": null,
      "fileType": "历史建筑平立剖面测绘图片",
      "filePath": "ccb8f07ed2544a69b1de4afee2ea79df.dwg",
      "fileExt": null,
      "fileSpace": null,
      "fileUserId": null,
      "fileUserName": null
    },
    {
      "createBy": "admin",
      "createTime": "2023-11-08 21:34:24",
      "updateBy": "admin",
      "updateTime": "2023-11-08 21:34:24",
      "fileHistoricalBuildId": "1559479328438050818",
      "fileId": "1722246192965017601",
      "fileName": "扬美（历）-19_t3.dwg",
      "fileTypeId": null,
      "fileType": "历史建筑平立剖面测绘图片",
      "filePath": "0fc2621dfeea40e4aee30f520bd0ed5f.dwg",
      "fileExt": null,
      "fileSpace": null,
      "fileUserId": null,
      "fileUserName": null
    },
    {
      "createBy": "admin",
      "createTime": "2023-11-08 21:34:24",
      "updateBy": "admin",
      "updateTime": "2023-11-08 21:34:24",
      "fileHistoricalBuildId": "1559479328438050818",
      "fileId": "1722246192973406209",
      "fileName": "扬美（历）-17_t3.dwg",
      "fileTypeId": null,
      "fileType": "历史建筑平立剖面测绘图片",
      "filePath": "4842cb793f9b4eb1a6b55af05b94644f.dwg",
      "fileExt": null,
      "fileSpace": null,
      "fileUserId": null,
      "fileUserName": null
    },
    {
      "createBy": "admin",
      "createTime": "2023-11-08 21:34:24",
      "updateBy": "admin",
      "updateTime": "2023-11-08 21:34:24",
      "fileHistoricalBuildId": "1559479328438050818",
      "fileId": "1722246192985989121",
      "fileName": "扬美（历）-14_t3.dwg",
      "fileTypeId": null,
      "fileType": "历史建筑平立剖面测绘图片",
      "filePath": "cb85986506bd4031a4a0ee4634951581.dwg",
      "fileExt": null,
      "fileSpace": null,
      "fileUserId": null,
      "fileUserName": null
    },
    {
      "createBy": "admin",
      "createTime": "2023-11-08 21:34:24",
      "updateBy": "admin",
      "updateTime": "2023-11-08 21:34:24",
      "fileHistoricalBuildId": "1559479328438050818",
      "fileId": "1722246193002766337",
      "fileName": "扬美（历）-08_t3.dwg",
      "fileTypeId": null,
      "fileType": "历史建筑平立剖面测绘图片",
      "filePath": "75a846250f254e9d9511702be725f04e.dwg",
      "fileExt": null,
      "fileSpace": null,
      "fileUserId": null,
      "fileUserName": null
    },
    {
      "createBy": "admin",
      "createTime": "2023-11-08 21:34:24",
      "updateBy": "admin",
      "updateTime": "2023-11-08 21:34:24",
      "fileHistoricalBuildId": "1559479328438050818",
      "fileId": "1722246193015349249",
      "fileName": "扬美（历）-09_t3.dwg",
      "fileTypeId": null,
      "fileType": "历史建筑平立剖面测绘图片",
      "filePath": "715d50f401f54eebb9d8c139e26b0e40.dwg",
      "fileExt": null,
      "fileSpace": null,
      "fileUserId": null,
      "fileUserName": null
    },
    {
      "createBy": "admin",
      "createTime": "2023-11-08 21:34:24",
      "updateBy": "admin",
      "updateTime": "2023-11-08 21:34:24",
      "fileHistoricalBuildId": "1559479328438050818",
      "fileId": "1722246193023737857",
      "fileName": "扬美（历）-10_t3.dwg",
      "fileTypeId": null,
      "fileType": "历史建筑平立剖面测绘图片",
      "filePath": "9c959a8972fb4eb6a05bca9b0b9e6f15.dwg",
      "fileExt": null,
      "fileSpace": null,
      "fileUserId": null,
      "fileUserName": null
    },
    {
      "createBy": "admin",
      "createTime": "2023-11-08 21:34:24",
      "updateBy": "admin",
      "updateTime": "2023-11-08 21:34:24",
      "fileHistoricalBuildId": "1559479328438050818",
      "fileId": "1722246193032126465",
      "fileName": "扬美（历）-04_t3.dwg",
      "fileTypeId": null,
      "fileType": "历史建筑平立剖面测绘图片",
      "filePath": "12829c78be4b481d8b985225738bed86.dwg",
      "fileExt": null,
      "fileSpace": null,
      "fileUserId": null,
      "fileUserName": null
    },
    {
      "createBy": "admin",
      "createTime": "2023-11-08 21:34:24",
      "updateBy": "admin",
      "updateTime": "2023-11-08 21:34:24",
      "fileHistoricalBuildId": "1559479328438050818",
      "fileId": "1722246193044709377",
      "fileName": "扬美（历）-05_t3.dwg",
      "fileTypeId": null,
      "fileType": "历史建筑平立剖面测绘图片",
      "filePath": "0b258cb25ab9496cb1ce4894beed137d.dwg",
      "fileExt": null,
      "fileSpace": null,
      "fileUserId": null,
      "fileUserName": null
    },
    {
      "createBy": "admin",
      "createTime": "2023-11-08 21:34:24",
      "updateBy": "admin",
      "updateTime": "2023-11-08 21:34:24",
      "fileHistoricalBuildId": "1559479328438050818",
      "fileId": "1722246193053097986",
      "fileName": "扬美（历）-06_t3.dwg",
      "fileTypeId": null,
      "fileType": "历史建筑平立剖面测绘图片",
      "filePath": "6d5c1c5881294b989a0f4944ddaace02.dwg",
      "fileExt": null,
      "fileSpace": null,
      "fileUserId": null,
      "fileUserName": null
    },
    {
      "createBy": "admin",
      "createTime": "2023-11-08 21:34:24",
      "updateBy": "admin",
      "updateTime": "2023-11-08 21:34:24",
      "fileHistoricalBuildId": "1559479328438050818",
      "fileId": "1722246193061486593",
      "fileName": "政府公布的文2020.10.16.pdf",
      "fileTypeId": null,
      "fileType": "公布文件",
      "filePath": "f1ac4b118a1e4ac19e6ab06df41f5812.pdf",
      "fileExt": null,
      "fileSpace": null,
      "fileUserId": null,
      "fileUserName": null
    }
  ],
  "disclosureTime": "2020-10-16",
  "disclosureFlag": "1",
  "districtCode": "450105000000",
  "historicalBuildImages": [
    {
      "createBy": "admin",
      "createTime": "2023-11-08 00:00:00",
      "updateBy": "admin",
      "updateTime": "2023-11-08 00:00:00",
      "imageMeasureId": "1559479328438050818",
      "imageId": "1722246193095041026",
      "imageName": "扬美(历)-04④-①立面.jpg",
      "imageAuthor": null,
      "imageDate": null,
      "imagePath": "5a8df9dd0c0642f0be47fbf9da5e2d78.jpg",
      "imageType": "侧立面"
    },
    {
      "createBy": "admin",
      "createTime": "2023-11-08 00:00:00",
      "updateBy": "admin",
      "updateTime": "2023-11-08 00:00:00",
      "imageMeasureId": "1559479328438050818",
      "imageId": "1722246193107623937",
      "imageName": "扬美(历)-05A-D立面.jpg",
      "imageAuthor": null,
      "imageDate": null,
      "imagePath": "22158660dfdb4a008017dcf37fe1f234.jpg",
      "imageType": "侧立面"
    },
    {
      "createBy": "admin",
      "createTime": "2023-11-08 00:00:00",
      "updateBy": "admin",
      "updateTime": "2023-11-08 00:00:00",
      "imageMeasureId": "1559479328438050818",
      "imageId": "1722246193116012546",
      "imageName": "壁画1.jpg",
      "imageAuthor": null,
      "imageDate": null,
      "imagePath": "649e1852be4a4d089eb1cbe3d1db14cd.jpg",
      "imageType": "建筑细部"
    },
    {
      "createBy": "admin",
      "createTime": "2023-11-08 00:00:00",
      "updateBy": "admin",
      "updateTime": "2023-11-08 00:00:00",
      "imageMeasureId": "1559479328438050818",
      "imageId": "1722246193124401153",
      "imageName": "629A3042.jpg",
      "imageAuthor": null,
      "imageDate": null,
      "imagePath": "189a33b96dd041b69e64a59d09baafbb.jpg",
      "imageType": "正立面"
    },
    {
      "createBy": "admin",
      "createTime": "2023-11-08 00:00:00",
      "updateBy": "admin",
      "updateTime": "2023-11-08 00:00:00",
      "imageMeasureId": "1559479328438050818",
      "imageId": "1722246193132789761",
      "imageName": "扬美(历)-01D-A立面.jpg",
      "imageAuthor": null,
      "imageDate": null,
      "imagePath": "449de891dc7a45b594fadc8ab5fafda4.jpg",
      "imageType": "正立面"
    }
  ],
  "source": "GX_Buildings"
}