{
  "A2_content": "-1- 柳州市三江侗族自治县林溪镇平岩村\n\n第二批中国传统村落、第一批广西传统村落\n\n \n\n一、村落概况\n\n平岩村位于林溪镇南端的林溪河畔，南距县城约 20 公里，通过 632 县道到达县城大约需要半小时车程。平岩村由马鞍、平寨、岩寨、平坦 4 个村寨组成，“平岩”取“平寨”“岩寨”各一字得名。平岩村域占地面积约17.84平方公里，约有960户、6900 人，以侗族为主，杨、吴、陈等姓氏人口居多。2013 年 8 月，平岩村成功申报入选第二批中国传统村落。\n\n二、历史源流\n\n平岩村地处著名的程阳八寨景区，是程阳八寨三个行政村其中之一（平岩村、程阳村和平铺村）。平岩村的居民是侗族人，是自古定居还是迁徙而来，较难考证。尽管平岩村的形成时间不易考证，\n\n但至少可以推断，自唐伊始，便有“蛋人”（南方沿海从事渔业的水上居民）、汉族移民迁入三江，并有可能迁徙至平岩村所在的地理位置，与当地居民共同生活。清代以来，现平岩村所在地逐渐形成了 8 个村寨，即平岩村的平寨、岩寨、马鞍、平坦，程阳村的大寨、懂寨，以及平铺村的吉昌、平铺。相传程姓和阳姓两家人最早来此居住，“程阳”地名由此而来，俗称“程阳八寨”。平岩村的平寨、岩寨、马鞍是程阳八寨景区最核心的 3 个村寨。\n\n三、村落格局\n\n平岩村建于丘陵河谷之间的平坦地带，村落整体依山面水，村前是阡陌田园，村后是苍翠山林，与自然山水融为一体，关系和谐。马鞍、平寨和岩寨三个村寨在地理位置上相对集中，呈组团式布\n\n局，林溪河蜿蜒穿过这三个村寨。而平坦屯偏于平岩村西侧一隅，与马鞍、平寨和岩寨相距约 1公里，但其格局也是背山面水。\n\n \n\n平岩的村寨以鼓楼坪（即鼓楼前方或近旁的小广场）为公共中心，公共建筑（戏台、井亭、寨门\n\n等）和民居围绕鼓楼而建，在空间布局上呈现内聚向心的特征。一直以来，鼓楼作为村寨中最高的建筑，高耸、挺拔，从视觉上控制着整个村寨。进入平岩村后不难发现，一座鼓楼、一片鼓楼坪、一座戏台是侗寨的“标配”。\n\n马鞍寨位于平岩村最南边的一个土坡脚下，三面环水，形似马鞍，故称“马鞍寨”。马鞍寨的鼓楼坪位于村寨中心的半山处，四通八达，向西通过程阳风雨桥（始建于 1912年）连通外界，向东经过合龙风雨桥（始建于 1814 年）可达平寨，向北在合龙桥头左转就是岩寨，向南跨林溪河便是马鞍寨门。\n\n平岩村有 5 座年代久远的风雨桥连通各个侗寨，除了程阳风雨桥、合龙风雨桥外，万寿桥（始建于 1920 年）、频安桥（建于清末道光年间）是岩寨连通外界和其他村寨的主要通路，普济桥（又称孝庙桥，始建于明正德年间）则可通往程阳村大\n\n \n\n寨。为了方便居民出行，当地还新建了聚福桥连通岩寨和平寨。\n\n四、传统建筑\n\n（一）传统建筑概况\n\n为了适应当地江河密布、气候炎热、潮湿多雨的地理气候环境，平岩村传统建筑沿等高线分布，依山傍水，形态多样，以“干栏式”民居为主。平岩村传统民居多采用穿斗式木构架，以石块筑基座，杉木作构架，木板作封闭围合，开窗较小。屋顶多采用悬山顶，青瓦屋面。\n\n侗族村落中的鼓楼、风雨桥、戏台等传统公共建筑，无不展现出侗族工匠精湛的营造技艺。同时，侗族工匠还积极吸收和借鉴其他地区、其他民族先进的建筑营造技艺，不断推动侗族木构建筑营造技艺的创新与发展。\n\n \n\n（二）马安鼓楼\n\n侗族基于血缘宗族关系的聚居方式，赋予了侗族村寨以鲜明的向心性和边界特征。鼓楼正是其向心性最为明显的标志，是侗族的族徽寨胆，承载着族姓标志、聚众议事、击鼓报信、礼仪庆典、休息娱乐等多重功能。马安鼓楼位于马鞍寨中心，始建于清嘉庆年间，1985 年曾进行维修，是自治区级文物保护单位。\n\n \n\n马安鼓楼占地约 70 平方米，平面呈方形，边长 8.4 米，面阔三间。马安鼓楼的结构独特精巧。鼓楼四周由 12 根边柱构成第一层柱网序列，墙体采用木栅格；鼓楼内部以 4 根杉木巨柱作为主承重柱，构成第二层柱网序列，主柱中心设火塘，形成空间的向心性焦点。鼓楼 4 根主承重柱之间用穿柱连接，形成井筒式内柱环，并以横梁连接外围边柱。边柱与主承重柱将内外柱网环套形成双筒体系，不仅扩大了鼓楼底层的使用空间，还极大增强了鼓楼的结构刚度。\n\n马安鼓楼为七层，高度达 12.6 米，采用四檐四角的重檐攒尖顶形式。鼓楼以侗族人民崇拜的杉树为原型，形成下大上小的塔楼形。层层内收的屋檐、白色的封檐板、起翘的檐角以及檐角上形态优美的灰塑，共同构成了鼓楼楼身极富韵律感的外观。在鼓楼的顶端，宝顶直接与楼身相连而形成整体，宝顶上装饰有象征吉祥的葫芦宝串，寓意村寨在鼓楼的庇护下，远离灾祸，吉祥如意。\n\n \n\n除了马安鼓楼，平岩村的平寨独柱鼓楼、平寨鼓楼、岩寨鼓楼、岩寨老鼓楼、平坦鼓楼等也是广西侗族鼓楼建筑的代表，充分展示了比例协调、均衡对称、规整完美的侗族木构建筑营造艺术。\n\n \n\n \n\n \n\n（三）程阳风雨桥\n\n风雨桥是侗族的重要公共建筑，不仅具有交通功能，还融合了娱乐、观赏等多重功能。风雨桥创造性地结合桥、廊、亭为一体，展现出侗族浓郁的民族风格和独特的建筑技艺。\n\n程阳风雨桥，又称程阳永济桥，位于马鞍寨，全国重点文物保护单位，是目前保存最好、规模最大的风雨桥。风雨桥始建于 1912年，1924 年完工；在 1937年和 1983年它遭受洪水侵袭，部分结构因\n\n此受损，但令人庆幸的是，灾后它按原貌得到了修复。郭沫若先生曾为程阳风雨桥题写“程阳桥”的匾名，并赋诗赞美其独特魅力：\n\n艳说林溪风雨桥，桥长廿丈四寻高。\n\n重瓴联阁怡神巧，列砥横流入望遥。\n\n竹木一身坚胜铁，茶林万载茁新苗。\n\n何时得上三江道，学把犁锄事体劳。\n\n程阳风雨桥为石墩木面翅式桥型，全长 77.76米，桥廊宽 3.75 米，桥顶高 11.52米。风雨桥采用两台三墩四孔，墩台上建有 5 座塔阁式桥亭和 19间桥廊，桥亭以墩台为中心对称分布，五重亭檐，亭廊相连，浑然一体，雄伟壮观。\n\n中央桥亭的设计尤为独特，由重檐正方形屋面\n\n及六角攒尖顶构成，高达 7.8米。中央桥亭两侧的桥亭为正方形重檐四角攒尖顶，高 7 米。最外两侧的桥亭为正方形歇山重檐顶，高 6.5米。这三组桥亭巧妙采用了三种屋顶形式，屋顶均饰以彩色宝葫芦，象征风调雨顺，五谷丰登。桥中部三座桥亭的顶层屋面使用筒瓦做法，并加以粉饰，进一步突出了程阳桥立面造型上的主次关系。\n\n在结构方面，程阳桥采用密式悬臂托架简支梁体系。两端桥亭采用抬梁与穿斗混合构架，局部抬高屋面形成重檐歇山，美观大方。中央桥亭采用叠顶做法，在正方形构架上加两根短柱和一根雷公柱，构成六角攒尖顶结构；短柱上设棂窗，其上挑出顶檐，以曲板吊顶。这种做法以叠顶的轻巧灵活\n\n \n\n来强调密檐上升收分的层次感，使得中央桥亭自然而然地成为风雨桥的视觉焦点。\n\n（四）程阳戏台\n\n侗族人民爱歌善歌，每寨必有戏台，常建于鼓楼旁边或与传统民居相结合。程阳戏台平面简洁，主要由舞台、辅助用房组成，在前台与后台一侧加偏房，内设火塘，既作为戏台的辅助用房，也是人们平常休息谈天的场所。戏台底部抬高，以利于观众视线的通达。\n\n \n\n（五）寨门\n\n平岩村的寨门作为村寨的防卫重点，设在村寨周围的主要路口上，以防御土匪的侵扰，具有“一夫当关，万夫莫开”之势。平岩村的寨门多采用干栏楼阁式。冲边寨门建成于 1947 年，为自治区级文物保护单位，其地理位置极为优越，一侧紧邻小溪，一侧依靠山坡，形成了天然的防御屏障。冲边寨门属干栏楼阁式，以四根大柱作为主承重柱，直立于寨门中央，稳固而结实，另外四根檐柱则将整个结构连接成一体，使得寨门更加稳定和安全。寨门底层作为迎来送往的通道，方便村民的日常出入；同时，两侧还设有座椅，供人们休憩之用。寨门二层围合成储藏空间，用于存放物品，增加了寨门的实用性和功能性。\n\n \n\n五、历史要素与非物质文化遗产\n\n（一）历史环境要素\n\n除了鼓楼、风雨桥、寨门、吊脚楼式民居外，平岩村还有多处古井亭、萨坛、石碑等别具侗寨特色的历史遗存，距今都有一两百年的历史。平岩村的古井多由青石块砌成，并辅以古朴的凉亭，遮阴避雨，不少古井亭沿用至今，村民在此打水、洗衣、闲聊交流，颇有生活韵味和清幽之美。萨坛则是由青石砌成的堡垒状石坛，坛外种有一株古老的风水树，坛内则用白火岩点排成花纹，用于敬奉侗族人民的祖先女神。此外，村内还有一座有名的石碑放置于思源井亭，碑文记载：“平寨饮水，幸党恩泽，饮水思源，建亭以志之，名曰思源亭”。\n\n \n\n \n\n（二）非物质文化遗产\n\n侗族木构建筑营造技艺是三江侗族自治县最出色的民族民间传统文化表现形式，于 2006年列入第一批国家级非物质遗产名录。\n\n侗族人民是天生的艺术家，民间有许多建筑才能高超的工匠，平岩村的杨善仁、杨似玉、杨求诗等都是代表性传承人。杨似玉家祖祖辈辈都是当地有名的工匠，1997 年香港回归时广西壮族自治区人民政府赠给香港特别行政区的珍贵礼物“同心桥”，就是杨似玉和他的父亲杨善仁依据程阳风雨桥的结构比例精心制作的。2014 年新建的平寨新鼓楼，是目前侗族地区最大、最雄伟的独柱鼓楼，由杨求诗担任墨师。在建造楼、桥和民居时，侗族\n\n工匠都不需要图纸，仅凭简单的竹签（一根画有特殊符号的半边竹竿，俗称“香竿”）为标尺，靠着独特的“墨师文”（一种侗族建筑建造符号，由建造者沾墨在竹签上写下一个个符号，区别每根木材的用处和位置）作设计标注，使用普通的木匠工具和木料就能建造出各式各样造型美观的建筑物，有的建筑物历经百年仍保存完好。\n\n表 1 平岩村侗族木构建造技术传承谱系及授徒情况 \n\n | 代别 | | 姓名 | | 性别 | | 出生年月 | | 文化程度 | | 传承方式 | \n\n | 第一代 | | 杨唐富 | | 男 | | 不详 | | 不详 | | 家族传承 | \n\n | 第一代 | | 莫杰强 | | 男 | | 不详 | | 不详 | | 师传 | \n\n | 第二代 | | 杨善仁 | | 男 | | 1925 年 | | 初中 | | 家族传承 | \n\n | 第二代 | | 吴家德 | | 男 | | 不详 | | 不详 | | 师传 | \n\n | 第二代 | | 吴国强 | | 男 | | 不详 | | 不详 | | 师传 | \n\n | 第三代 | | 杨似玉 | | 男 | | 1955.08 | | 小学 | | 家族传承 | \n\n | 第三代 | | 杨玉吉 | | 男 | | 1963.04 | | 初中 | | 家族传承 | \n\n | 第四代 | | 杨求诗 | | 男 | | 1963.10 | | 初中 | | 师传 | \n\n | 第四代 | | 杨朝水 | | 男 | | 1967.04 | | 小学 | | 师传 | \n\n | 第四代 | | 杨玉军 | | 男 | | 1968.07 | | 小学 | | 师传 | \n\n | 第四代 | | 杨愿陆 | | 男 | | 1970.03 | | 小学 | | 师传 | \n\n | 第四代 | | 李书文 | | 男 | | 1969.10 | | 小学 | | 师传 | \n\n | 第四代 | | 吴永兆 | | 男 | | 1970.10 | | 小学 | | 师传 | \n\n | 第四代 | | 杨斌旅 | | 男 | | 1986.05 | | 大专 | | 家族传承 | \n\n | 第四代 | | 杨顺旋 | | 男 | | 1988.10 | | 大专 | | 家族传承 | \n\n | 第四代 | | 杨全景 | | 男 | | 1986.05 | | 高中 | | 家族传承 | \n\n平岩村主要的传统民族节日有韭菜节、尝新节、四月八、牛节、太阳节等；民间活动主要有斗牛、赛芦笙、坐夜、月也、多耶等。传统手工艺有：侗族服饰的刺绣技艺，侗族银饰艺术品的制作技艺，侗族传统风味酸肉、酸鸭、酸鱼、酸菜等腌制办法以及藤编、竹编、草编等日常用品的加工技术等。在平岩村能体验到最具特色的民俗风情当属侗族“百家宴”（又称“合拢饭”“长桌宴”），这是一种集体举办的传统宴席，平岩村是发源地之一。举办宴席时，家家户户拿出独具侗家特色美食：浓香的糯饭、香醇的糯米酒、酸鱼、酸肉等。“百家宴”场面隆重、热烈壮观，全村老少盛装跳芦笙舞，唱耶歌欢迎宾客。",
  "source": "广西传统村落丛书",
  "volume": "中册",
  "chapter": "第四章 黔桂古道传统村落",
  "entry_type": "village",
  "village_number": 1,
  "structureType": "干栏式",
  "build_year": "明（1368-1644年）",
  "city": "柳州市"
}