{
  "building_name": "荣昌隆",
  "measureName": "荣昌隆",
  "requestDate": "2023-11-23 10:51:05",
  "valueIntroduction": "原为洋杂铺，现为居住。\n\n该建筑是沙脊街上为数不多仍具木质结构外墙的建筑，它的形式在一定程度上反映了旧时沙脊街的建筑风貌。",
  "nowFunction": "居住",
  "buildFloor": 2,
  "buildArea": 84.0,
  "buildLandArea": 42.0,
  "propertyType": "私产",
  "propertyOwner": "苏翠英",
  "city": "北海市",
  "county": "海城区",
  "build_year": "民国（1911-1949年）",
  "address": "民建一街95号",
  "A2_content": "立面全部以现代材料粉刷抹平，传统木质结构外墙全部遭到破坏。立面被破坏之前，该建筑是沙脊街上为数不多仍具木质结构外墙的建筑，它的形式在一定程度上反映了旧时沙脊街的建筑风貌。",
  "status": "PASS",
  "publishTime": "2009-12-01 00:00:00",
  "protectionRepair": "未修缮",
  "buildingQuality": "中",
  "protectionRepairDept": "规划局",
  "buildingApproval": "已批准",
  "signTab": "已挂牌",
  "cityType": "国家历史文化名城",
  "measureFlag": "1",
  "publishInfo": "已发布",
  "cityLevel": "自治区级",
  "historicalBuildtFiles": [
    {
      "createBy": "admin",
      "createTime": "2023-11-23 10:51:31",
      "updateBy": "admin",
      "updateTime": "2023-11-23 10:51:31",
      "fileHistoricalBuildId": "1559479344263159809",
      "fileId": "1727520223218450434",
      "fileName": "04第一批+批文.pdf",
      "fileTypeId": null,
      "fileType": "公布文件",
      "filePath": "79782699d06f452b99630825c7247956.pdf",
      "fileExt": null,
      "fileSpace": null,
      "fileUserId": null,
      "fileUserName": null
    }
  ],
  "disclosureTime": "2009-12-01",
  "disclosureFlag": "1",
  "districtCode": "450502000000",
  "historicalBuildImages": [
    {
      "createBy": "admin",
      "createTime": "2023-11-23 00:00:00",
      "updateBy": "admin",
      "updateTime": "2023-11-23 00:00:00",
      "imageMeasureId": "1559479344263159809",
      "imageId": "1727520223256199170",
      "imageName": "侧面2.jpg",
      "imageAuthor": null,
      "imageDate": null,
      "imagePath": "54db26e574dc4be0a91909ca870875fd.jpg",
      "imageType": "侧立面"
    },
    {
      "createBy": "admin",
      "createTime": "2023-11-23 00:00:00",
      "updateBy": "admin",
      "updateTime": "2023-11-23 00:00:00",
      "imageMeasureId": "1559479344263159809",
      "imageId": "1727520223268782082",
      "imageName": "003.jpg",
      "imageAuthor": null,
      "imageDate": null,
      "imagePath": "04ed3f478d3742e99fbd03eeb2f4ad8f.jpg",
      "imageType": "建筑细部"
    },
    {
      "createBy": "admin",
      "createTime": "2023-11-23 00:00:00",
      "updateBy": "admin",
      "updateTime": "2023-11-23 00:00:00",
      "imageMeasureId": "1559479344263159809",
      "imageId": "1727520223277170689",
      "imageName": "侧面3.jpg",
      "imageAuthor": null,
      "imageDate": null,
      "imagePath": "531e297580df424a8515dfbee3954af3.jpg",
      "imageType": "外部全景"
    },
    {
      "createBy": "admin",
      "createTime": "2023-11-23 00:00:00",
      "updateBy": "admin",
      "updateTime": "2023-11-23 00:00:00",
      "imageMeasureId": "1559479344263159809",
      "imageId": "1727520223289753601",
      "imageName": "正面1.jpg",
      "imageAuthor": null,
      "imageDate": null,
      "imagePath": "4b6684b99b0e4e239d0820ce3d11d569.jpg",
      "imageType": "正立面"
    }
  ],
  "source": "GX_Buildings"
}