{
  "A2_content": "-13- 钦州市浦北县石埇镇坡子坪村委老城村\n\n第一批广西传统村落\n\n \n\n一、村落概况\n\n浦北县石埇镇坡子坪村老城村，紧靠南流社区、长山村，地势北高南低，属低山丘陵地区。老城村距离石埇镇约 18 公里。截止至 2018 年，全村人口约 321 人，村民年人均收入约 6800 元/年，主要种植马铃薯、青花菜等农作物。\n\n \n\n老城村香翰屏旧居中的增城子、嘉李园分别始建于 1936 年、1929 年，由于部分建材来源于广州等地，筹建时间较长，地理位置坐落在广西浦北县石埇镇坡子坪村委会老城村。这是一座集西方建筑风格和中国传统古建筑特色于一体的别墅式、庄园式的将军府邸，共有大小房屋 116 间，占地面积 35亩，建筑面积 5044 平方米，分别由“增城子”与“嘉李园”组成。\n\n2017 年 12 月 8 日，香翰屏旧居列为广西壮族自治区级文物保护单位，保护范围为“增城子”以外墙作为文物边界，向外延伸 5 米内；“嘉李园”以围墙作为文物边界，向外延伸 5 米内。\n\n二、村落格局\n\n老城村地处丘陵地带，依山而建，有良好的生态环境，北面为海拔 500 米的高山，其余均为农田用地，自然环境优美，生态景观丰富。\n\n \n\n老城村建有 1 条主要村道与外围乡镇进行联系，道路宽度约 3.5 米。此外，村庄内还建有 3 条巷路，巷路宽约 2 米，均已硬化。\n\n三、传统建筑\n\n（一）香翰屏旧居\n\n香翰屏故居建于 1936 年，是一座集西方建筑风格和中国传统古建筑特色于一体的庄园式、别墅式将军府邸，坐西向东。故居如今主体部分保存尚好，局部附楼、炮楼坍塌破败。香翰屏是原广东省合浦县人，一代儒将，曾任国民党第三军军长、三省司令，参加过淞沪会战。故居分为“增城子”和“嘉李园”两部分，分别始建于 1936 年、1929 年，由于部分建材来源于广州等地，筹建时间较长，历经十年才竣工。俯视故居全貌，设计独特，中西合璧，布局对称合理，建造工艺精湛，艺术特色浓厚。香翰屏故居具有极高的历史、科学和艺术价值，并对研究民国时期岭南中西合璧式庄园具有重要的实物参考价值。\n\n \n\n \n\n（二）“增城子”\n\n“增城子”依山筑就，气势磅礴。城外是一片平原，视野开阔，五谷飘香；城内四周有围墙，城墙高约 5 米，用黄泥土、沙、石灰砌筑，十分坚固。南门楼与北门楼是进入城内的唯一通道，两者相对而立，是由砖瓦木构造的中式楼房，三开间，两层高，小巧玲珑。南北两门楼的不同之处仅在于屋顶及琉璃瓦饰图案的不同：北门楼屋顶为硬山顶，正脊为博古脊，两边为人字封火山墙，尾端塑以博古；南门楼屋顶为歇山顶，正脊为博古脊，戗脊尾端塑以飞凤，两门相互呼应。楼上楼下与墙角两边，均布有哨、炮洞，此乃重兵护园之所。此外，两门楼左右两旁均设有卫生间、仓库、马圈、牛栏、猪舍等。\n\n主体为三进两厢、硬山顶的二层建筑。每进建有房、厅、花园，后进南、北角分别设有炮楼。房屋采用砖、木、石、水泥、钢筋、琉璃瓦等建造，\n\n共有大小房间 116 间。庭院配置十分讲究，林木茂盛、景观宜人。\n\n \n\n四套居室的外墙均有密密麻麻、凹凸不平的蜂窝形隔音墙。楼顶为平屋面，铺有方形的红色隔热地砖。\n\n \n\n \n\n \n\n前座中间为正门，坐西南向东北，门前廊设计为戏台。将军府凡有喜庆之事，均请戏班子在此唱戏娱乐。门前有一小广场，是练兵或观众看戏席座的地方。正门设有横栊、直栊、板门三层防范设施；前座二层高，二楼为一开口厅，走廊可以连通到中座。屋檐滴水处饰青色琉璃瓦。屋脊塔顶高出瓦面，饰有青色琉璃瓦构件，封山两边饰有云纹博古构件。\n\n前座与中座之间有一个长方形大天井，天井旁布有 5 根大圆柱。前座门厅两侧与天井左右两侧相接。南北两边各有一座三房两厅的西式别墅楼房，是主人房，楼房设计及面积、装饰一致。一楼由一个圆形门进入，分别有楼梯间、客厅、卧室、卫生间，墙壁洁白光滑。客厅天花有吊灯座，地板铺有不同颜色的八角形花瓷砖，显得十分豪华、美观大方。每个客厅前均有一个半圆形大阳台；上下二层\n\n中座为一大门厅，与正门相对相通，有大板门。一楼两边有大小两个客厅，二楼可与前座、后座相通，四向走廊相对连接，可谓四通八达，结构与一楼相同。中座与后座之间有一个正方形天井，四面建有圆柱。天井的南北两向各设有一个大厅，圆门纱窗，宽阔、明亮。左右两厅对称，建有两个花圃，种有名花名树，幽深僻静，舒雅别致。庭院外侧各有直屋一栋，两层结构，为佣仆住舍。\n\n后座中间为祖公厅，摆设神台，有“金玉满堂”的字样。两边有对联，神台中央设置有香翰屏将军遗照，妻妾遗照列于左右。祖公厅的顶梁柱浮雕刻有“中華民國丙子年丁酉月丁酉日乙巳時行牆升梁吉”字样。\n\n西北角和东北角分别有一座三层的炮楼，并且每层布满枪眼和炮洞，与前座两门楼相呼应，承担着护园责任。炮楼屋脊设计独特，正脊为博古脊，\n\n两边为镬耳封火山墙，以博古收尾。后座背后为一个大型花果园，植有名贵花草和名品果树。\n\n \n\n2.“嘉李园”\n\n“嘉李园”建在“增城子”后侧的小山坡上，按七星座和五行设计，建有窝庐居、松庐居、橄榄居、画云阁、观音堂等楼、台、亭、阁，每座小楼的命名均有所寓意。\n\n嘉李园正门向东，两边有厢房，一层高，简称窝庐居。正门背后为松庐居，简称为“谣光星”，象征海王星，一层高，屋檐四周外有圆柱，走廊铺有花地板砖，为一厅一房。橄榄居象征金星，两层高，屋檐走廊有圆柱。画云阁（玉衡星）象征水星，实际是一座藏书楼，此楼在民国时期曾收藏过一部比较完整的钦定四库全书（其数量约有两卡车之多）；画云阁为二层结构，桥型塔式楼顶的设计，盖琉璃瓦，屋檐四周有圆形柱头。观音堂为单间一层，内设有神台、观音座莲神像，屋顶为塔式建筑构造，盖琉璃瓦。观音堂旁边是土地神、有凉亭一座，堂前为官厅，是香公用来会客的场所。后门楼为一栋二层两间别墅式小洋楼。\n\n \n\n（三）祖公厅\n\n祖公厅位于香翰屏故居北侧，坐西向东，占地面积广，四周围以高大的城墙，四角设有炮楼，如今仅余东北、东南角两座炮楼尚存。前座门厅后面是宽敞开阔的场地，可容纳大量村民在此开展活动。后座祖公厅是两进两厢布局，东、南、北三面环廊，建筑整体已修缮翻新，墙面抹白，铺灰色瓦，悬山顶。\n\n \n\n \n\n \n\n四、历史要素和非物质文化遗产\n\n老城村现保留有 1 棵名木古树，为荔枝树，树龄多在 110 年之间，位于香翰屏旧居的东北面，树木长势良好。\n\n \n\n自 2012 年乐民镇中秋“舞青龙”文化项目列入自治区级非物质文化遗产后，每年农历八月十五晚上，浦北县石埇镇都举行隆重的舞青龙活动，并且已成为当地一个独具特色、隆重而热烈的传统节日，具有鲜明、浓郁的地方民俗色彩。当地群众在乐民街东、西、南、北、新区五条街各制作一条青龙，龙身用香蕉叶扎制而成，龙长几十至一百米，每条龙可容纳一二百人，并配有锣鼓、唢呐等敲打伴奏。",
  "source": "广西传统村落丛书",
  "volume": "下册",
  "chapter": "第七章 海上丝绸之路传统村落",
  "entry_type": "village",
  "village_number": 13,
  "city": "钦州市"
}