{
  "A2_content": "-59- 阳朔县高田镇朗梓村\n\n第二批中国传统村落 第一批广西传统村落\n\n \n\n一、村落概况\n\n朗梓村位于阳朔县高田镇西侧，村落距高田镇镇区约 8 公里，距阳朔县城约 18 公里。村落形成于清初，距今已有 300 多年，村名原为“榄子”，因村中族人勤耕苦读，人才辈出，清代考取功名者甚多，清光绪 3 年该村进士覃梦榕将村名改为“朗梓”。“朗”有明朗、清澈、高洁之意，“梓”是故乡的代称，“朗梓”即为月明故乡之意，彰显了村落的人文底蕴。抗日战争时期，村中传统建筑瑞枝公祠曾作为阳朔县立国民中学的临时教学点，西北侧的碉楼也曾作为抗击日军侵略的有力据点，承受了枪炮的洗礼。村内现有人口 523 人，以壮族为\n\n主，由覃、何、钟三个姓氏构成。\n\n二、历史源流\n\n据《覃族谱书》记载，朗梓村始建于清顺治时期，其始祖覃正遥，系广西庆远宜山县人，原为明末农民起义军领袖李自成部下一名战将，驻守北平，在清兵入关大败北平的战役中南撤，后随南明驻柳州总兵抗清，在桂柳、长沙一带作战。抗清失败后，覃公独自轻骑回乡，路经阳朔朗梓，见土地肥沃，水秀山清，便久居下来，后又邀其兄与侄来此定居，同甘共苦，繁衍子孙。至清咸丰年间，已人丁兴旺，家财富有，于是请匠购料，扩建居所，经历代发展，成如今规模。\n\n \n\n朗梓族人重诗书文风，清代时期有“一门四进士，同堂两县官”的美谈，此“门”为光绪初年举人覃孟昌故居，该宅登科及第者有 6 人，其中覃兆昉曾于同治十二年拜翰林院大学士。近代后人们继续秉承家族好学之风，考入国内一流院校深造者甚多。\n\n三、村落格局\n\n村落的选址有“五龙抢珠”的传奇故事，朗梓的开基始祖覃正遥兵败归乡途经此地时，遇得仙翁托梦，将一宝珠交与他保管，遂引来五龙争抢，惊醒后，发觉脚下的沃土与梦中之物一一对应，于是决定在此繁衍生息，成就了今日的朗梓。故事虚实虽无法考证，但五龙与珠如今依然静静伏于田野之上。从高空俯瞰，宝珠，正是村落传统建筑群西侧紧紧依偎的小土丘，土丘高约 30 米，长宽不过百米，郁郁葱葱，圆润如珠；五龙，则是村落四周匍\n\n匐着的五岭，五岭从不同方向上逶迤而来，在此终结，形成了传说中“五龙抢珠”的格局。村落便选址于五岭尽头的良田中，一条溪流从北侧丘陵和“宝珠”土丘中穿过，滋润着整个村落及周边农田。\n\n \n\n \n\n四、传统建筑\n\n村落现存传统建筑群较为集中，保存完好的主要为瑞枝公祠建筑群、碉楼、覃氏家祠及若干民宅。建筑多为青砖灰瓦，封火墙高大，每户墙体相连，随地势高低错落。古建筑群结构严密、布局精巧、规划整齐有序，建筑风格颇具岭南广府之风。\n\n（一）瑞枝公祠建筑群\n\n据《覃族谱书》记载，覃氏族人于明末清初从宜州迁徙至此，以覃世叁工（瑞枝）为首的这一支自立公祠，从 1825 年开始兴建，历经三代人的努力，到 1865 年历时 40 年落成，公祠建成后以世叁工的号“瑞枝”命名。公祠为三进三开间南侧带护厝形式，护厝设两层，为公祠的辅助用房；公祠北侧为一民居，相传为族人覃兆勲所建，民居与公祠共用一个入户大门及庭院，庭院足有两百多平方米，民居北侧是其配套用房，沿民居及公祠的进深方向纵向延伸，贯穿入户门至炮楼，旧时应为佣人房、储物间、厨房等功能空间。瑞枝公祠、民居及其辅助用房、碉楼共同构成了一座规整严密的建筑群，从公祠与民居高度统一的建筑体量、风格推测，该建筑群应为同期所建，但细节上也有等级、尊卑关系的体现。两座建筑同为三进三开间的平面布局，民居的开间宽度较公祠略大，但三进的高度以及封\n\n火山墙高度均比公祠稍矮，公祠正脊的装饰也比民居要精美繁复。\n\n \n（来源：莫凯琳 摄）\n\n整个建筑群依地形逐级上升，公祠及民居的整体层高比普通民居突出，公祠二进正厅主檩下方到室内地坪高度达 9 米，使得建筑群整体威严气派。两侧的辅助用房依功能需求灵活布局，既有横向带天井布局，也有纵向结合巷道布局，加上外围的连廊、围墙、碉楼，形成了鳞次栉比，富有变化的立面组合。祠堂首进敞廊下两根檐柱高擎，“瑞枝公祠”四字用花岗石凿成并镶嵌于大门正方，大门屋檐下整齐排列着 7 幅长度不等的壁画，画有乌鸦戏水、春燕衔泥、渔翁钓鲤等。正厅檐下、檩下山墙处也都装饰着色彩艳丽的飞禽走兽、花鸟绿植壁画，为空间增色不少。山墙跨入大门是族人聚会的大厅，\n\n \n\n（来源：经菁 绘）\n\n为阳朔县仅存的旧时防匪防盗建筑。\n\n越过大厅与天井，则是三开间的祭堂，供奉祖先牌位。\n\n瑞枝公祠组团西端保留有一座七层碉楼，外观呈长方形，碉楼高约 30 米，共七层，用条石青砖砌成，四面均有瞭望窗和射击口，登上可俯瞰全村及四周环境。\n\n \n\n（二）覃氏家祠\n\n据《覃族谱书》记载，覃氏家祠建于道光年间，位于村落西侧山丘之上，俯瞰民居建筑群。受地形所限，家祠为三开间三合院式天井院落，砖木混合结构，由天井、厢房、正堂组成，正堂开间宽度较厢房与天井窄。家祠门开正面，两侧开弧形窗，二层之上为漏窗，造型别致，工艺细腻。大门上方及立面檐墙顶上覆绿色琉璃瓦，既突显家祠入口，又与后山绿树互为映衬，相得益彰。\n\n（三）76-78 号民居\n\n76-78 号民居位于瑞枝公祠南侧，为三开间两进三天井院落。入户天井一侧墙体原与巷道呈一定\n\n \n\n（来源：莫凯琳 摄）\n\n \n\n（来源：莫凯琳 摄）\n\n交角，屋主平行于巷道加建一板墙体，与原墙体形成一处三角形杂物间，空间处理颇为巧妙。整座民居外部朴素，内部装饰较考究。\n\n（四）建筑特色\n\n朗梓村民居多在\n\n一进房屋前设入户天井庭院，天井正中或旁侧设入户门楼，门楼设于旁侧时，天井正中置影壁装饰。\n\n入户门楼通常为人字坡屋面，两侧山墙或以马头墙为装饰，或做前后起翘，造型轻巧，门楼视高度可设二层做储物或瞭望值守空间。\n\n五、历史要素\n\n朗梓的古建筑除上述保存完好的宗祠、古民居、碉楼等传统建筑外，还有护村石墙、牌匾、木雕、骨雕等历史文化遗存。其中长 150 米，高 7 米的护村古石墙，墙上藤蔓攀沿，人们喻之为“藤墙”。每到春暖花开，繁花似锦，人们又喻之为“花墙”。\n\n另有一石碑位于瑞枝公祠河对岸，字迹模糊，隐约可见“高寨众公议牧牛地”、“嘉庆廿五年”等字样。",
  "source": "广西传统村落丛书",
  "volume": "上册",
  "chapter": "第二章 湘桂古道传统村落",
  "entry_type": "village",
  "village_number": 59,
  "structureType": "砖木混合结构",
  "build_year": "清（1644-1911年）",
  "city": "桂林市"
}