{
  "building_name": "龙川公凉亭",
  "measureName": "龙川公凉亭",
  "requestName": "管理员",
  "requestPhone": "17034642998",
  "requestDate": "2024-01-26 08:43:21",
  "valueIntroduction": "龙川公凉亭位于桂林市灌阳县文市镇瑶上屯，为清代砖木结构单层建筑，占地面积约30平方米。该凉亭地处永州至灌阳的古道节点，采用开敞式布局，推测为双面开门或三面落柱的典型驿道凉亭形制，主梁可能存有建造年代题记。其砖木混合构造体现了清代桂北地区交通设施的实用特征，简朴的形制与当地民居工艺一脉相承。作为红军长征途经的重要历史见证，该建筑承载了从清代商贸往来至近代革命活动的双重历史记忆，民间\"红军亭\"的称谓更强化了其红色文化价值。现状建筑质量较差且未经修缮，但挂牌保护身份凸显了其作为灌阳县古道遗存与革命文物的典型意义。",
  "nowFunction": "其他",
  "structureType": "砖木结构",
  "buildFloor": 1,
  "buildArea": 30.0,
  "buildLandArea": 30.0,
  "propertyType": "公产",
  "propertyOwner": "灌阳县文市镇瑶上村民委员会",
  "city": "桂林市",
  "county": "灌阳县",
  "build_year": "清（1644-1911年）",
  "address": "灌阳县文市镇瑶上屯",
  "status": "PASS",
  "publishTime": "2023-07-20 00:00:00",
  "protectionRepair": "未修缮",
  "buildingQuality": "差",
  "protectionRepairDept": "住建局",
  "buildingApproval": "已批准",
  "signTab": "已挂牌",
  "cityType": "国家历史文化名城",
  "batch": "第一批",
  "publishInfo": "已发布",
  "cityLevel": "自治区级",
  "nowFunctionMsg": "景观设施",
  "historicalBuildtFiles": [
    {
      "createBy": "admin",
      "createTime": "2024-01-29 15:26:31",
      "updateBy": "admin",
      "updateTime": "2024-01-29 15:26:31",
      "fileHistoricalBuildId": "1750680792025395202",
      "fileId": "1751869414166622210",
      "fileName": "灌政发〔2023〕8号灌阳县人民政府关于公布灌阳县第一批历史建筑名录的通知.pdf",
      "fileTypeId": null,
      "fileType": "公布文件",
      "filePath": "a77989c206d4443d9261ca62ff2cd48b.pdf",
      "fileExt": null,
      "fileSpace": null,
      "fileUserId": null,
      "fileUserName": null
    }
  ],
  "districtCode": "450327000000",
  "historicalBuildImages": [
    {
      "createBy": "admin",
      "createTime": "2024-01-29 00:00:00",
      "updateBy": "admin",
      "updateTime": "2024-01-29 00:00:00",
      "imageMeasureId": "1750680792025395202",
      "imageId": "1751869414204370945",
      "imageName": "侧立面.jpg",
      "imageAuthor": null,
      "imageDate": null,
      "imagePath": "638088428f0649059cf2edf7945db6a2.jpg",
      "imageType": "侧立面"
    },
    {
      "createBy": "admin",
      "createTime": "2024-01-29 00:00:00",
      "updateBy": "admin",
      "updateTime": "2024-01-29 00:00:00",
      "imageMeasureId": "1750680792025395202",
      "imageId": "1751869414212759554",
      "imageName": "建筑细部3.jpg",
      "imageAuthor": null,
      "imageDate": null,
      "imagePath": "abcd203d2da347acbe9c97929ebe4b4d.jpg",
      "imageType": "建筑细部"
    },
    {
      "createBy": "admin",
      "createTime": "2024-01-29 00:00:00",
      "updateBy": "admin",
      "updateTime": "2024-01-29 00:00:00",
      "imageMeasureId": "1750680792025395202",
      "imageId": "1751869414225342465",
      "imageName": "建筑细部2.jpg",
      "imageAuthor": null,
      "imageDate": null,
      "imagePath": "18fa9d5ace5a46e19215f9cf8d019096.jpg",
      "imageType": "建筑细部"
    },
    {
      "createBy": "admin",
      "createTime": "2024-01-29 00:00:00",
      "updateBy": "admin",
      "updateTime": "2024-01-29 00:00:00",
      "imageMeasureId": "1750680792025395202",
      "imageId": "1751869414233731074",
      "imageName": "建筑细部1.jpg",
      "imageAuthor": null,
      "imageDate": null,
      "imagePath": "ca9b98a958624313ad3dd49fdf0f0fd2.jpg",
      "imageType": "建筑细部"
    },
    {
      "createBy": "admin",
      "createTime": "2024-01-29 00:00:00",
      "updateBy": "admin",
      "updateTime": "2024-01-29 00:00:00",
      "imageMeasureId": "1750680792025395202",
      "imageId": "1751869414242119682",
      "imageName": "内部全景.jpg",
      "imageAuthor": null,
      "imageDate": null,
      "imagePath": "0cf55cc253fe458493660a7b02c5c2a0.jpg",
      "imageType": "内部全景"
    },
    {
      "createBy": "admin",
      "createTime": "2024-01-29 00:00:00",
      "updateBy": "admin",
      "updateTime": "2024-01-29 00:00:00",
      "imageMeasureId": "1750680792025395202",
      "imageId": "1751869414254702593",
      "imageName": "正立面.jpg",
      "imageAuthor": null,
      "imageDate": null,
      "imagePath": "8f353af9fff1425fad63ff0d4404458b.jpg",
      "imageType": "正立面"
    }
  ],
  "source": "GX_Buildings",
  "A2_content": "龙川公凉亭位于桂林市灌阳县文市镇瑶上屯，为清代砖木结构单层建筑，占地面积约30平方米。该凉亭地处永州至灌阳的古道节点，采用开敞式布局，推测为双面开门或三面落柱的典型驿道凉亭形制，主梁可能存有建造年代题记。其砖木混合构造体现了清代桂北地区交通设施的实用特征，简朴的形制与当地民居工艺一脉相承。作为红军长征途经的重要历史见证，该建筑承载了从清代商贸往来至近代革命活动的双重历史记忆，民间\"红军亭\"的称谓更强化了其红色文化价值。现状建筑质量较差且未经修缮，但挂牌保护身份凸显了其作为灌阳县古道遗存与革命文物的典型意义。"
}